yafowil.widget.dynatree-1.7-py3.9-nspkg.pth
yafowil/widget/dynatree/__init__.py
yafowil/widget/dynatree/example.py
yafowil/widget/dynatree/tests.py
yafowil/widget/dynatree/widget.py
yafowil/widget/dynatree/resources/widget.css
yafowil/widget/dynatree/resources/widget.js
yafowil/widget/dynatree/resources/jquery.dynatree/GPL-LICENSE.txt
yafowil/widget/dynatree/resources/jquery.dynatree/MIT-License.txt
yafowil/widget/dynatree/resources/jquery.dynatree/jquery.dynatree.js
yafowil/widget/dynatree/resources/jquery.dynatree/jquery.dynatree.min.js
yafowil/widget/dynatree/resources/jquery.dynatree/skin/icons.gif
yafowil/widget/dynatree/resources/jquery.dynatree/skin/loading.gif
yafowil/widget/dynatree/resources/jquery.dynatree/skin/ui.dynatree.css
yafowil/widget/dynatree/resources/jquery.dynatree/skin/vline.gif
yafowil/widget/dynatree/resources/jquery.dynatree/skin-bootstrap/icons.png
yafowil/widget/dynatree/resources/jquery.dynatree/skin-bootstrap/loading.gif
yafowil/widget/dynatree/resources/jquery.dynatree/skin-bootstrap/ui.dynatree.css
yafowil/widget/dynatree/resources/jquery.dynatree/skin-bootstrap/vline.gif
yafowil/widget/dynatree/resources/jquery.dynatree/skin-vista/icons.gif
yafowil/widget/dynatree/resources/jquery.dynatree/skin-vista/loading.gif
yafowil/widget/dynatree/resources/jquery.dynatree/skin-vista/ui.dynatree.css
yafowil_widget_dynatree-1.7.dist-info/licenses/LICENSE.rst
yafowil_widget_dynatree-1.7.dist-info/METADATA
yafowil_widget_dynatree-1.7.dist-info/WHEEL
yafowil_widget_dynatree-1.7.dist-info/entry_points.txt
yafowil_widget_dynatree-1.7.dist-info/namespace_packages.txt
yafowil_widget_dynatree-1.7.dist-info/top_level.txt
yafowil_widget_dynatree-1.7.dist-info/RECORD
